confdantic/__init__.py
confdantic/confdantic.py
confdantic-0.1.2.dist-info/METADATA
confdantic-0.1.2.dist-info/WHEEL
confdantic-0.1.2.dist-info/licenses/LICENSE
confdantic-0.1.2.dist-info/RECORD
