Metadata-Version: 2.4
Name: confdantic
Version: 0.1.2
Summary: Generate user-friendly configuration files from Pydantic models
Project-URL: Repository, https://github.com/zigai/confdantic
Project-URL: Issues, https://github.com/zigai/confdantic/issues
Project-URL: Homepage, https://github.com/zigai/confdantic
Author-email: zigai <ziga.ivansek@gmail.com>
License: MIT License
License-File: LICENSE
Keywords: confdantic,config,pydantic,pydantic-config,pydantic-config-file,pydantic-configuration,pydantic-toml-comments,pydantic-yaml-comments,toml,toml-configuration,yaml,yaml-configuration
Classifier: Intended Audience :: Developers
Classifier: License :: OSI Approved :: MIT License
Classifier: Operating System :: OS Independent
Classifier: Programming Language :: Python
Classifier: Programming Language :: Python :: 3
Classifier: Programming Language :: Python :: 3 :: Only
Classifier: Programming Language :: Python :: 3.10
Classifier: Programming Language :: Python :: 3.11
Classifier: Programming Language :: Python :: 3.12
Classifier: Programming Language :: Python :: 3.13
Classifier: Programming Language :: Python :: 3.14
Classifier: Topic :: Software Development :: Libraries :: Python Modules
Classifier: Typing :: Typed
Requires-Python: >=3.10
Requires-Dist: objinspect>=0.3.1
Requires-Dist: pydantic>=2.12.3
Requires-Dist: ruamel-yaml>=0.18.6
Requires-Dist: toml>=0.10.2
Requires-Dist: tomlkit>=0.12.3
Provides-Extra: dev
Requires-Dist: codespell; extra == 'dev'
Requires-Dist: coverage; extra == 'dev'
Requires-Dist: mypy; extra == 'dev'
Requires-Dist: pre-commit; extra == 'dev'
Requires-Dist: pytest; extra == 'dev'
Requires-Dist: ruff; extra == 'dev'
Provides-Extra: test
Requires-Dist: coverage; extra == 'test'
Requires-Dist: pytest; extra == 'test'
